Metadata-Version: 1.0
Name: probability-gaussian-binomial
Version: 0.3
Summary: Gaussian and binomial distributions
Home-page: UNKNOWN
Author: Gopi Mehta
Author-email: gopimehta60@gmail.com
License: UNKNOWN
Platform: UNKNOWN
